{
  "gitSyncId": "68e5397b43db3c4a6ee11f42_29ca923c-e499-4ea6-9585-ad41ada80af5",
  "id": "Opportunity Details Health_Housing.openHousingModal",
  "pluginId": "js-plugin",
  "pluginType": "JS",
  "unpublishedAction": {
    "actionConfiguration": {
      "encodeParamsToggle": true,
      "jsArguments": [],
      "paginationType": "NONE",
      "timeoutInMillisecond": 10000
    },
    "collectionId": "Opportunity Details Health_Housing",
    "confirmBeforeExecute": false,
    "datasource": {
      "isAutoGenerated": false,
      "name": "UNUSED_DATASOURCE",
      "pluginId": "js-plugin"
    },
    "dynamicBindingPathList": [
      {
        "key": "body"
      }
    ],
    "fullyQualifiedName": "Housing.openHousingModal",
    "name": "openHousingModal",
    "pageId": "Opportunity Details Health",
    "runBehaviour": "MANUAL",
    "userSetOnLoad": false
  }
}