{
  "animateLoading": true,
  "borderRadius": "{{appsmith.theme.borderRadius.appBorderRadius}}",
  "bottomRow": 240,
  "boxShadow": "none",
  "canEscapeKeyClose": true,
  "canOutsideClickClose": true,
  "children": [
    {
      "bottomRow": 170,
      "canExtend": true,
      "detachFromLayout": true,
      "displayName": "Canvas",
      "dynamicBindingPathList": [],
      "hideCard": true,
      "isDeprecated": false,
      "isDisabled": false,
      "isLoading": false,
      "isVisible": true,
      "key": "bj1hzds0qk",
      "leftColumn": 0,
      "minHeight": 178,
      "parentColumnSpace": 1,
      "parentId": "7yaqciz86m",
      "parentRowSpace": 1,
      "renderMode": "CANVAS",
      "rightColumn": 0,
      "shouldScrollContents": false,
      "topRow": 0,
      "type": "CANVAS_WIDGET",
      "version": 1,
      "widgetId": "zuqvfvsmqp",
      "widgetName": "Canvas18"
    }
  ],
  "detachFromLayout": true,
  "displayName": "Modal",
  "dynamicBindingPathList": [
    {
      "key": "borderRadius"
    }
  ],
  "dynamicHeight": "FIXED",
  "dynamicTriggerPathList": [],
  "height": 178,
  "hideCard": false,
  "iconSVG": "/static/media/icon.4975978e9a961fb0bfb4e38de7ecc7c5.svg",
  "isCanvas": true,
  "isDeprecated": false,
  "isLoading": false,
  "key": "wfqo0czcgr",
  "leftColumn": 0,
  "maxDynamicHeight": 9000,
  "minDynamicHeight": 24,
  "parentColumnSpace": 1,
  "parentId": "0",
  "parentRowSpace": 1,
  "renderMode": "CANVAS",
  "rightColumn": 0,
  "searchTags": [
    "dialog",
    "popup",
    "notification"
  ],
  "shouldScrollContents": true,
  "topRow": 0,
  "type": "MODAL_WIDGET",
  "version": 2,
  "widgetId": "7yaqciz86m",
  "widgetName": "Modal1",
  "width": 532
}