{
  "gitSyncId": "65a6ac3f671c3345d0868803_65f80f9fa6769c39716bd16f",
  "id": "Opportunity Details Housing_createNewHouseScraper.createNewHouseScraper",
  "pluginId": "js-plugin",
  "pluginType": "JS",
  "unpublishedAction": {
    "actionConfiguration": {
      "encodeParamsToggle": true,
      "jsArguments": [],
      "paginationType": "NONE",
      "timeoutInMillisecond": 10000
    },
    "collectionId": "Opportunity Details Housing_createNewHouseScraper",
    "confirmBeforeExecute": false,
    "datasource": {
      "isAutoGenerated": false,
      "name": "UNUSED_DATASOURCE",
      "pluginId": "js-plugin"
    },
    "dynamicBindingPathList": [
      {
        "key": "body"
      }
    ],
    "fullyQualifiedName": "createNewHouseScraper.createNewHouseScraper",
    "name": "createNewHouseScraper",
    "pageId": "Opportunity Details Housing",
    "runBehaviour": "MANUAL",
    "userSetOnLoad": true
  }
}