{
  "gitSyncId": "67daf58d0ca7fb78d41c818a_3caf75ab-7f97-4390-b7fd-c4a755718d97",
  "id": "User details_utils.openBankAccountModal",
  "pluginId": "js-plugin",
  "pluginType": "JS",
  "unpublishedAction": {
    "actionConfiguration": {
      "encodeParamsToggle": true,
      "jsArguments": [],
      "paginationType": "NONE",
      "timeoutInMillisecond": 10000
    },
    "collectionId": "User details_utils",
    "confirmBeforeExecute": false,
    "datasource": {
      "isAutoGenerated": false,
      "name": "UNUSED_DATASOURCE",
      "pluginId": "js-plugin"
    },
    "dynamicBindingPathList": [
      {
        "key": "body"
      }
    ],
    "fullyQualifiedName": "utils.openBankAccountModal",
    "name": "openBankAccountModal",
    "pageId": "User details",
    "runBehaviour": "MANUAL",
    "userSetOnLoad": false
  }
}