{
  "gitSyncId": "69c585f2bc614d160753a915_9316140d-f639-42f7-85ba-9cdcf1069f09",
  "id": "Opportunity Details Loan Copy_Actions.findFamilyMember",
  "pluginId": "js-plugin",
  "pluginType": "JS",
  "unpublishedAction": {
    "actionConfiguration": {
      "encodeParamsToggle": true,
      "jsArguments": [
        {
          "name": "id"
        }
      ],
      "paginationType": "NONE",
      "timeoutInMillisecond": 10000
    },
    "collectionId": "Opportunity Details Loan Copy_Actions",
    "confirmBeforeExecute": false,
    "datasource": {
      "isAutoGenerated": false,
      "name": "UNUSED_DATASOURCE",
      "pluginId": "js-plugin"
    },
    "dynamicBindingPathList": [
      {
        "key": "body"
      }
    ],
    "fullyQualifiedName": "Actions.findFamilyMember",
    "name": "findFamilyMember",
    "pageId": "Opportunity Details Loan Copy",
    "runBehaviour": "MANUAL",
    "userSetOnLoad": false
  }
}